rust_code_analysis_python-0.0.4.dist-info/METADATA
rust_code_analysis_python-0.0.4.dist-info/WHEEL
rust_code_analysis_python-0.0.4.dist-info/licenses/LICENSE
rust_code_analysis_python.libs/libgcc_s-e52197c3.so.1
rust_code_analysis_python.libs/libstdc++-405035b3.so.6
rust_code_analysis_python/__init__.py
rust_code_analysis_python/rust_code_analysis_python.cpython-312-aarch64-linux-musl.so
rust_code_analysis_python-0.0.4.dist-info/RECORD
