Metadata-Version: 2.4
Name: rust-code-analysis-python
Version: 0.0.4
Classifier: Programming Language :: Rust
Classifier: Development Status :: 3 - Alpha
Classifier: Intended Audience :: Developers
Classifier: Topic :: Software Development :: Quality Assurance
Classifier: Topic :: Software Development :: Compilers
License-File: LICENSE
Summary: Python bindings for rust-code-analysis
Keywords: rust,python,code,analysis,complexity,metrics,refactoring
Author-email: Luigi Finetti <luigi@finetti.com.ar>
License: MPL-2.0
Requires-Python: >=3.7
Project-URL: Bug Tracker, https://github.com/luigig44/rust-code-analysis-python/issues
Project-URL: Source Code, https://github.com/luigig44/rust-code-analysis-python
